{"data_id": "dce57a02-ccd7-4bef-acd1-537644684662", "url": "https://trabajito.com.bo/public/trabajo/regente-farmaceutico-pando-cobija-w7nq7mjvdl", "title": "regente farmac\u00e9utico pando", "company": "farmacorp", "location": " cobija", "type_job": " medicina y salud", "job_description": "Farmacorp se encuentra en b squeda de un a Regente Farmac utico Base  Cobija  Pando Objetivo del puesto Administrar y supervisar la dispensaci n de medicamentos  asegurando el cumplimiento de normativas vigentes  la correcta gesti n del inventario y el liderazgo del equipo de trabajo en la sucursal asignada Funciones  Requisitos  Se ofrece  Si cumples con el perfil  postula ahora a trav s de trabajito com bo ", "date_published": "2025-06-03T00:00:00", "date_expiration": "2025-05-04T00:00:00", "date_saved": "2025-04-04t14:12:54.876803", "date_saved_iso": "2025-04-04T14:12:54.876803", "domain": "trabajito.com.bo", "status": "Active"}